yoshi_seals-2.0.3692068298.dist-info/METADATA
yoshi_seals-2.0.3692068298.dist-info/top_level.txt
yoshi_seals-2.0.3692068298.dist-info/RECORD
yoshi_seals-2.0.3692068298.dist-info/WHEEL
yoshi_seals-2.0.3692068298.dist-info/LICENSE
test/__init__.py
test/test_process.py
yoshi_seals/__init__.py
yoshi_seals/eigen/eigen.py
yoshi_seals/eigen/__init__.py
yoshi_seals/shared/__init__.py
yoshi_seals/shared/array.cpython-38-x86_64-linux-gnu.so
yoshi_seals/insert/insert.py
yoshi_seals/insert/__init__.py
yoshi_seals/write/__init__.py
yoshi_seals/write/write.py
yoshi_seals/scan/__init__.py
yoshi_seals/scan/scan.py
yoshi_seals/process/__init__.py
yoshi_seals/process/process.cpython-38-x86_64-linux-gnu.so
