Metadata-Version: 2.1
Name: yoshi-seals
Version: 2.0.3692068298
Summary: Numeric Calculus python module in the topic of Linear Algebra
Home-page: https://github.com/HideyoshiNakazone/Seals-NumericCalculus.git
Author: Vitor Hideyoshi
Author-email: vitor.h.n.batista@gmail.com
Classifier: Programming Language :: Python :: 3
Classifier: License :: OSI Approved :: GNU General Public License v2 (GPLv2)
Classifier: Operating System :: OS Independent
Requires-Python: >=3.8
License-File: LICENSE
Requires-Dist: numpy
Requires-Dist: pandas
